{
    "records": [
        {
            "Autobiography": [], 
            "Service": [], 
            "Obituary": [], 
            "DOB": "1910-01-15", 
            "DVD": [], 
            "Collected_Works": [], 
            "DOD": "1963-11-04", 
            "Member": [], 
            "Symposium": [], 
            "Memoir": [], 
            "Degree": [], 
            "complete_name": "Fisz, Marek", 
            "Oral_History": [], 
            "Selected_Works": [], 
            "In_Memoriam": [], 
            "ims_id": "fisz__marek", 
            "public_record_txt": "", 
            "Art_Exhibition": [], 
            "link_ls": [
                {
                    "href": "http://www.ams.org/mathscinet/search/author.html?mrauthid=257656", 
                    "anchor": "MathSciNet"
                }, 
                {
                    "href": "http://zbmath.org/authors/?q=ai:fisz.marek", 
                    "anchor": "zbMATH"
                }, 
                {
                    "href": "http://genealogy.math.ndsu.nodak.edu/id.php?id=36991", 
                    "anchor": "Math. Genealogy"
                }, 
                {
                    "href": "http://academic.research.microsoft.com/Author/18660934", 
                    "anchor": "Microsoft Academic: Fisz, Marek"
                }
            ], 
            "Position": [], 
            "Honor": [
                {
                    "category": "honor", 
                    "text": "IMS Fellow", 
                    "year": "1959", 
                    "link_ls": ""
                }
            ], 
            "Festschrift": [], 
            "Death_Notice": [], 
            "Education": [
                {
                    "category": "degree", 
                    "school": "Politechnika Wroc&amp;\\#322;awska", 
                    "thesis_title": "Quality Control of Mass Production by Variables", 
                    "year": "1950", 
                    "link_ls": [
                        {
                            "href": "http://genealogy.math.ndsu.nodak.edu/id.php?id=36991"
                        }
                    ], 
                    "type": "Ph.D."
                }
            ], 
            "Endowment": [], 
            "Archive": [], 
            "Biography": []
        }
    ], 
    "books": []
}