{
    "records": [
        {
            "Autobiography": [], 
            "Service": [], 
            "Obituary": [], 
            "DVD": [], 
            "Collected_Works": [], 
            "Member": [], 
            "Symposium": [], 
            "Memoir": [], 
            "Degree": [], 
            "complete_name": "Geman, Donald J.", 
            "Oral_History": [], 
            "Selected_Works": [], 
            "In_Memoriam": [], 
            "ims_id": "geman__donald_j", 
            "public_record_txt": "", 
            "Art_Exhibition": [], 
            "link_ls": [
                {
                    "category": "homepage", 
                    "href": "http://www.cis.jhu.edu/people/faculty/geman/index.html", 
                    "rel": "homepage"
                }, 
                {
                    "href": "http://www.ams.org/mathscinet/search/author.html?mrauthid=72330", 
                    "anchor": "MathSciNet"
                }, 
                {
                    "href": "http://zbmath.org/authors/?q=ai:geman.donald", 
                    "anchor": "zbMATH"
                }, 
                {
                    "href": "http://genealogy.math.ndsu.nodak.edu/id.php?id=12778", 
                    "anchor": "Math. Genealogy"
                }, 
                {
                    "href": "http://academic.research.microsoft.com/Author/47783170", 
                    "anchor": "Microsoft Academic: D. Geman"
                }, 
                {
                    "href": "http://academic.research.microsoft.com/Author/2374558", 
                    "anchor": "Microsoft Academic: Donald Geman"
                }
            ], 
            "Position": [], 
            "Honor": [
                {
                    "category": "honor", 
                    "text": "IMS Fellow", 
                    "year": "1997", 
                    "link_ls": ""
                }, 
                {
                    "category": "honor", 
                    "text": "IMS Medallion Lecturer", 
                    "year": "2012", 
                    "link_ls": ""
                }
            ], 
            "alt_ims_id": "geman__donald", 
            "Festschrift": [], 
            "Death_Notice": [], 
            "Education": [
                {
                    "category": "degree", 
                    "school": "Northwestern University", 
                    "thesis_title": "Horizontal-Window Conditioning and the Zeros of Stationary Processes", 
                    "year": "1970", 
                    "link_ls": [
                        {
                            "href": "http://genealogy.math.ndsu.nodak.edu/id.php?id=12778"
                        }
                    ], 
                    "type": "Ph.D."
                }
            ], 
            "Endowment": [], 
            "Archive": [], 
            "Biography": []
        }
    ], 
    "books": []
}