{
    "records": [
        {
            "Autobiography": [], 
            "Service": [], 
            "Obituary": [], 
            "DVD": [], 
            "Collected_Works": [], 
            "Member": [], 
            "Symposium": [], 
            "Memoir": [], 
            "Degree": [], 
            "complete_name": "Godambe, Vidyadhar P.", 
            "Oral_History": [], 
            "Selected_Works": [], 
            "In_Memoriam": [], 
            "ims_id": "godambe__v_p", 
            "public_record_txt": "", 
            "Art_Exhibition": [], 
            "link_ls": [
                {
                    "href": "http://www.ams.org/mathscinet/search/author.html?mrauthid=74370", 
                    "anchor": "MathSciNet"
                }, 
                {
                    "href": "http://zbmath.org/authors/?q=ai:godambe.vidyadhar-p", 
                    "anchor": "zbMATH"
                }, 
                {
                    "href": "http://genealogy.math.ndsu.nodak.edu/id.php?id=42242", 
                    "anchor": "Math. Genealogy"
                }, 
                {
                    "href": "http://academic.research.microsoft.com/Author/54414092", 
                    "anchor": "Microsoft Academic: Godambe, V. P."
                }, 
                {
                    "href": "http://academic.research.microsoft.com/Author/12807371", 
                    "anchor": "Microsoft Academic: Godambe, V. P."
                }
            ], 
            "Position": [], 
            "Honor": [
                {
                    "category": "honor", 
                    "text": "IMS Fellow", 
                    "year": "1972", 
                    "link_ls": ""
                }, 
                {
                    "category": "honor", 
                    "text": "The Royal Society of Canada, Fellow", 
                    "year": "2002", 
                    "link_ls": ""
                }
            ], 
            "alt_ims_id": "godambe__v", 
            "Festschrift": [], 
            "Death_Notice": [], 
            "Education": [
                {
                    "category": "degree", 
                    "school": "University of London", 
                    "thesis_title": "Robust and Non-Parametric Inference and Other General Criterea for Statistical Decisions", 
                    "year": "1958", 
                    "link_ls": [
                        {
                            "href": "http://genealogy.math.ndsu.nodak.edu/id.php?id=42242"
                        }
                    ], 
                    "type": "Ph.D."
                }
            ], 
            "Endowment": [], 
            "Archive": [], 
            "Biography": []
        }
    ], 
    "books": []
}