{
    "records": [
        {
            "Autobiography": [], 
            "Service": [], 
            "Obituary": [
                {
                    "title": "Zakkula Govindarajulu", 
                    "ref": "<t>Zakkula Govindarajulu.</t> ???", 
                    "author": "Anonymous", 
                    "bibtype": "misc", 
                    "year": "2011", 
                    "howpublished": "???", 
                    "topline": "misc govindarajulu__z:294966", 
                    "id": "govindarajulu__z:294966"
                }
            ], 
            "DOB": "1933-05-15", 
            "DVD": [], 
            "Collected_Works": [], 
            "DOD": "2010-12-05", 
            "Member": [], 
            "Symposium": [], 
            "Memoir": [], 
            "Degree": [], 
            "complete_name": "Govindarajulu, Z.", 
            "Oral_History": [], 
            "Selected_Works": [], 
            "In_Memoriam": [], 
            "ims_id": "govindarajulu__z", 
            "public_record_txt": "", 
            "Art_Exhibition": [], 
            "link_ls": [
                {
                    "category": "homepage", 
                    "href": "http://it.wikipedia.org/wiki/Zakkula_Govindarajulu", 
                    "rel": "homepage"
                }, 
                {
                    "href": "http://www.ams.org/mathscinet/search/author.html?mrauthid=75825", 
                    "anchor": "MathSciNet"
                }, 
                {
                    "href": "http://zbmath.org/authors/?q=ai:govindarajulu.zakkula", 
                    "anchor": "zbMATH"
                }, 
                {
                    "href": "http://zbmath.org/authors/?q=ai:govindarajulu-z.", 
                    "anchor": "zbMATH"
                }, 
                {
                    "href": "http://genealogy.math.ndsu.nodak.edu/id.php?id=89322", 
                    "anchor": "Math. Genealogy"
                }, 
                {
                    "href": "http://academic.research.microsoft.com/Author/12963891", 
                    "anchor": "Microsoft Academic: Govindarajulu, Zakkula"
                }
            ], 
            "Position": [], 
            "Honor": [
                {
                    "category": "honor", 
                    "text": "IMS Fellow", 
                    "year": "1974", 
                    "link_ls": ""
                }
            ], 
            "Festschrift": [], 
            "Image": [], 
            "Death_Notice": [], 
            "Education": [
                {
                    "category": "degree", 
                    "school": "University of Minnesota-Minneapolis", 
                    "thesis_title": "Central Limit Theorems and Asymptotic Efficiency for One Sample Non-Parametric Procedures", 
                    "year": "1961", 
                    "link_ls": [
                        {
                            "href": "http://genealogy.math.ndsu.nodak.edu/id.php?id=89322"
                        }
                    ], 
                    "type": "Ph.D."
                }
            ], 
            "Endowment": [], 
            "Archive": [], 
            "Biography": []
        }
    ], 
    "books": []
}