{
    "records": [
        {
            "Autobiography": [], 
            "Service": [], 
            "Obituary": [], 
            "DVD": [], 
            "Collected_Works": [], 
            "Member": [], 
            "Symposium": [], 
            "Memoir": [], 
            "Degree": [], 
            "complete_name": "Hoppe, Fred M.", 
            "Oral_History": [], 
            "Selected_Works": [], 
            "In_Memoriam": [], 
            "ims_id": "hoppe__fred_m", 
            "public_record_txt": "", 
            "Art_Exhibition": [], 
            "link_ls": [
                {
                    "category": "homepage", 
                    "href": "http://www.math.mcmaster.ca/fred/", 
                    "rel": "homepage"
                }, 
                {
                    "href": "http://www.ams.org/mathscinet/search/author.html?mrauthid=88120", 
                    "anchor": "MathSciNet"
                }, 
                {
                    "href": "http://zbmath.org/authors/?q=ai:hoppe.fred-m", 
                    "anchor": "zbMATH"
                }, 
                {
                    "href": "http://genealogy.math.ndsu.nodak.edu/id.php?id=7911", 
                    "anchor": "Math. Genealogy"
                }, 
                {
                    "href": "http://academic.research.microsoft.com/Author/52644801", 
                    "anchor": "Microsoft Academic: Hoppe, Fred M."
                }, 
                {
                    "href": "http://academic.research.microsoft.com/Author/12771169", 
                    "anchor": "Microsoft Academic: Hoppe, Fred M."
                }
            ], 
            "Position": [], 
            "Honor": [
                {
                    "category": "honor", 
                    "text": "IMS Fellow", 
                    "year": "1995", 
                    "link_ls": ""
                }
            ], 
            "alt_ims_id": "hoppe__fred", 
            "Festschrift": [], 
            "Death_Notice": [], 
            "Education": [
                {
                    "category": "degree", 
                    "school": "", 
                    "link_ls": [
                        {
                            "href": "http://genealogy.math.ndsu.nodak.edu/id.php?id=7911"
                        }
                    ], 
                    "type": "Ph.D.", 
                    "year": "year?"
                }
            ], 
            "Endowment": [], 
            "Archive": [], 
            "Biography": []
        }
    ], 
    "books": []
}