{
    "records": [
        {
            "Autobiography": [], 
            "Service": [], 
            "Obituary": [], 
            "DVD": [], 
            "Collected_Works": [], 
            "Member": [], 
            "Symposium": [], 
            "Memoir": [], 
            "Degree": [], 
            "complete_name": "Kadane, Joseph B.", 
            "Oral_History": [], 
            "Selected_Works": [], 
            "In_Memoriam": [], 
            "ims_id": "kadane__joseph_b", 
            "public_record_txt": "", 
            "Art_Exhibition": [], 
            "link_ls": [
                {
                    "category": "homepage", 
                    "href": "http://www.stat.cmu.edu/%7Ekadane/", 
                    "rel": "homepage"
                }, 
                {
                    "href": "http://www.ams.org/mathscinet/search/author.html?mrauthid=96625", 
                    "anchor": "MathSciNet"
                }, 
                {
                    "href": "http://zbmath.org/authors/?q=ai:kadane.joseph-b", 
                    "anchor": "zbMATH"
                }, 
                {
                    "href": "http://genealogy.math.ndsu.nodak.edu/id.php?id=41403", 
                    "anchor": "Math. Genealogy"
                }, 
                {
                    "href": "http://academic.research.microsoft.com/Author/10679055", 
                    "anchor": "Microsoft Academic: Kadane, Joseph B."
                }
            ], 
            "Position": [], 
            "Honor": [
                {
                    "category": "honor", 
                    "text": "IMS Fellow", 
                    "year": "1975", 
                    "link_ls": ""
                }, 
                {
                    "category": "honor", 
                    "text": "American Academy of Arts and Sciences, Fellow", 
                    "year": "2010", 
                    "link_ls": ""
                }
            ], 
            "alt_ims_id": "kadane__joseph", 
            "Festschrift": [], 
            "Death_Notice": [], 
            "Education": [
                {
                    "category": "degree", 
                    "school": "Stanford University", 
                    "thesis_title": "Comparison of Estimators in Simultaneous Equation Econometric Models when the Results are Small", 
                    "year": "1966", 
                    "link_ls": [
                        {
                            "href": "http://genealogy.math.ndsu.nodak.edu/id.php?id=41403"
                        }
                    ], 
                    "type": "Ph.D."
                }
            ], 
            "Endowment": [], 
            "Archive": [], 
            "Biography": []
        }
    ], 
    "books": []
}