{
    "records": [
        {
            "Autobiography": [], 
            "Service": [], 
            "Obituary": [], 
            "DVD": [], 
            "Collected_Works": [], 
            "Member": [], 
            "Symposium": [], 
            "Memoir": [], 
            "Degree": [], 
            "complete_name": "Kass, Robert E.", 
            "Oral_History": [], 
            "Selected_Works": [], 
            "In_Memoriam": [], 
            "ims_id": "kass__robert_e", 
            "public_record_txt": "", 
            "Art_Exhibition": [], 
            "link_ls": [
                {
                    "category": "homepage", 
                    "href": "http://www.stat.cmu.edu/~kass/", 
                    "rel": "homepage"
                }, 
                {
                    "href": "http://www.ams.org/mathscinet/search/author.html?mrauthid=98930", 
                    "anchor": "MathSciNet"
                }, 
                {
                    "href": "http://zbmath.org/authors/?q=ai:kass.robert-e", 
                    "anchor": "zbMATH"
                }, 
                {
                    "href": "http://genealogy.math.ndsu.nodak.edu/id.php?id=84682", 
                    "anchor": "Math. Genealogy"
                }, 
                {
                    "href": "http://academic.research.microsoft.com/Author/689784", 
                    "anchor": "Microsoft Academic: Kass, Robert E."
                }
            ], 
            "Position": [], 
            "Honor": [
                {
                    "category": "honor", 
                    "text": "IMS Fellow", 
                    "year": "1991", 
                    "link_ls": ""
                }, 
                {
                    "category": "honor", 
                    "text": "IMS Medallion Lecturer", 
                    "year": "1992", 
                    "link_ls": ""
                }, 
                {
                    "category": "honor", 
                    "text": "IMS Medallion Lecturer", 
                    "year": "2002", 
                    "link_ls": ""
                }
            ], 
            "alt_ims_id": "kass__robert", 
            "Festschrift": [], 
            "Image": [
                {
                    "src": "http://academic.research.microsoft.com/Photo/689784.jpg", 
                    "href": "http://stat.cmu.edu/~kass/06pic.jpg"
                }
            ], 
            "Death_Notice": [], 
            "Education": [
                {
                    "category": "degree", 
                    "school": "The University of Chicago", 
                    "thesis_title": "Riemannian Structure of Model Spaces: A Geometrical Approach to Inference", 
                    "year": "1980", 
                    "link_ls": [
                        {
                            "href": "http://genealogy.math.ndsu.nodak.edu/id.php?id=84682"
                        }
                    ], 
                    "type": "Ph.D."
                }
            ], 
            "Endowment": [], 
            "Archive": [], 
            "Biography": []
        }
    ], 
    "books": []
}