{
    "records": [
        {
            "Autobiography": [], 
            "Service": [], 
            "Obituary": [], 
            "DVD": [], 
            "Collected_Works": [], 
            "Member": [], 
            "Symposium": [], 
            "Memoir": [], 
            "Degree": [], 
            "complete_name": "Prakasa-Rao, B. L. S.", 
            "Oral_History": [], 
            "Selected_Works": [], 
            "In_Memoriam": [], 
            "ims_id": "prakasa-rao__b_l_s", 
            "public_record_txt": "", 
            "Art_Exhibition": [], 
            "link_ls": [
                {
                    "category": "homepage", 
                    "href": "http://www.isid.ac.in/~statmath/homepageblsp/index.html", 
                    "rel": "homepage"
                }, 
                {
                    "href": "http://zbmath.org/authors/?q=ai:prakasa-rao.b-s", 
                    "anchor": "zbMATH"
                }, 
                {
                    "href": "http://zbmath.org/authors/?q=ai:prakasa-rao.b-l-s", 
                    "anchor": "zbMATH"
                }, 
                {
                    "href": "http://academic.research.microsoft.com/Author/12954728", 
                    "anchor": "Microsoft Academic: B. L. S. Prakasa Rao"
                }, 
                {
                    "href": "http://academic.research.microsoft.com/Author/52127997", 
                    "anchor": "Microsoft Academic: B. L. S. Prakasa Rao"
                }, 
                {
                    "href": "http://academic.research.microsoft.com/Author/52646730", 
                    "anchor": "Microsoft Academic: B. L. S. Prakasa Rao"
                }
            ], 
            "Position": [], 
            "Honor": [
                {
                    "category": "honor", 
                    "text": "IMS Fellow", 
                    "year": "1983", 
                    "link_ls": ""
                }, 
                {
                    "category": "honor", 
                    "text": "Indian National Science Academy, Fellow", 
                    "year": "1984", 
                    "link_ls": ""
                }, 
                {
                    "category": "honor", 
                    "text": "Indian Academy of Sciences, Fellow", 
                    "year": "1992", 
                    "link_ls": ""
                }
            ], 
            "alt_ims_id": "prakasa-rao__b", 
            "Festschrift": [], 
            "Image": [], 
            "Death_Notice": [], 
            "Education": [], 
            "Endowment": [], 
            "Archive": [], 
            "Biography": []
        }
    ], 
    "books": []
}