{
    "records": [
        {
            "Autobiography": [], 
            "Service": [], 
            "Obituary": [], 
            "DVD": [], 
            "Collected_Works": [], 
            "Member": [], 
            "Symposium": [], 
            "Memoir": [], 
            "Degree": [], 
            "complete_name": "Raftery, Adrian E.", 
            "Oral_History": [], 
            "Selected_Works": [], 
            "In_Memoriam": [
                {
                    "title": "Bishnoedath Leo Raktoe", 
                    "ref": "<t>Bishnoedath Leo Raktoe.</t> <au>Pesotan, H. and Singh, R. S.</au>. ???", 
                    "author": "Pesotan, H. and Singh, R. S.", 
                    "bibtype": "misc", 
                    "year": "2010", 
                    "howpublished": "???", 
                    "topline": "misc raftery__adrian_e:572526", 
                    "id": "raftery__adrian_e:572526"
                }
            ], 
            "ims_id": "raftery__adrian_e", 
            "public_record_txt": "", 
            "Art_Exhibition": [], 
            "link_ls": [
                {
                    "category": "homepage", 
                    "href": "http://www.stat.washington.edu/raftery/", 
                    "rel": "homepage"
                }, 
                {
                    "href": "http://zbmath.org/authors/?q=ai:raftery.adrian-e", 
                    "anchor": "zbMATH"
                }, 
                {
                    "href": "http://academic.research.microsoft.com/Author/743892", 
                    "anchor": "Microsoft Academic: Raftery, Adrian"
                }
            ], 
            "Position": [], 
            "Honor": [
                {
                    "category": "honor", 
                    "text": "IMS Medallion Lecturer", 
                    "year": "1997", 
                    "link_ls": ""
                }, 
                {
                    "category": "honor", 
                    "text": "American Academy of Arts and Sciences, Fellow", 
                    "year": "2003", 
                    "link_ls": ""
                }, 
                {
                    "category": "honor", 
                    "text": "IMS Medallion Lecturer", 
                    "year": "2005", 
                    "link_ls": ""
                }, 
                {
                    "category": "honor", 
                    "text": "IMS Fellow", 
                    "year": "2007", 
                    "citation": "For seminal contributions to Bayesian model selection and computation, demography, clustering, and stochastic modeling, for influential and novel high-impact statistical applications, and for conscientious professional service", 
                    "link_ls": ""
                }, 
                {
                    "category": "honor", 
                    "text": "National Academy of Sciences, Member", 
                    "year": "2009", 
                    "link_ls": ""
                }
            ], 
            "alt_ims_id": "raftery__adrian", 
            "Festschrift": [], 
            "Image": [
                {
                    "src": "http://academic.research.microsoft.com/Photo/743892.jpg", 
                    "href": "http://www.stat.washington.edu/raftery/Raftery_crop2.jpg"
                }
            ], 
            "Death_Notice": [], 
            "Education": [], 
            "Endowment": [], 
            "Archive": [], 
            "Biography": []
        }
    ], 
    "books": []
}