{
    "records": [
        {
            "Autobiography": [], 
            "Service": [], 
            "Obituary": [], 
            "DVD": [], 
            "Collected_Works": [], 
            "Member": [], 
            "Symposium": [], 
            "Memoir": [], 
            "Degree": [], 
            "complete_name": "Stute, Winfried", 
            "Oral_History": [], 
            "Selected_Works": [], 
            "In_Memoriam": [], 
            "ims_id": "stute__winfried", 
            "public_record_txt": "", 
            "Art_Exhibition": [], 
            "link_ls": [
                {
                    "href": "http://www.ams.org/mathscinet/search/author.html?mrauthid=168505", 
                    "anchor": "MathSciNet"
                }, 
                {
                    "href": "http://zbmath.org/authors/?q=ai:stute.winfried", 
                    "anchor": "zbMATH"
                }, 
                {
                    "href": "http://genealogy.math.ndsu.nodak.edu/id.php?id=28353", 
                    "anchor": "Math. Genealogy"
                }, 
                {
                    "href": "http://academic.research.microsoft.com/Author/55225928", 
                    "anchor": "Microsoft Academic: Stute, Winfried"
                }, 
                {
                    "href": "http://academic.research.microsoft.com/Author/447663", 
                    "anchor": "Microsoft Academic: Stute, Winfried"
                }
            ], 
            "Position": [], 
            "Honor": [
                {
                    "category": "honor", 
                    "text": "IMS Fellow", 
                    "year": "1990", 
                    "link_ls": ""
                }
            ], 
            "Festschrift": [], 
            "Death_Notice": [], 
            "Education": [
                {
                    "category": "degree", 
                    "school": "Ruhr-Universit&auml;t Bochum", 
                    "thesis_title": "On Probabilistic Limit Theorems for the Isotrope Discrepancy = Wahrscheindlichkeitstheorische Grezwerts&auml;tze f&uuml;r die isotrope Diskrepanz", 
                    "year": "1975", 
                    "link_ls": [
                        {
                            "href": "http://genealogy.math.ndsu.nodak.edu/id.php?id=28353"
                        }
                    ], 
                    "type": "Ph.D."
                }
            ], 
            "Endowment": [], 
            "Archive": [], 
            "Biography": []
        }
    ], 
    "books": []
}